{
  "ノーブルクライ": 3.2,
  "リアルフォルゴーレ": 46.2,
  "セットアップ": 10.0,
  "クラウンウルル": 66.7,
  "サングラデーション": 4.4,
  "ルルフィーユ": 41.5,
  "ヴォルスター": 67.1,
  "マグナレガリア": 5.6,
  "ジロラータ": 8.8,
  "ダスク": 7.7,
  "バニーラビット": 13.3,
  "デスティネ": 34.5,
  "スノーリン": 72.8,
  "ニシノロッドマン": 37.1,
  "ホウオウストライク": 8.0,
  "メイショウイッカク": 25.1,
  "クロームクロス": 11.2,
  "キングスペード": 29.6,
  "ウルトラハート": 6.1,
  "コイオステソーロ": 2.2,
  "フィオリータ": 38.4,
  "キタノハイテイル": 33.0,
  "マイカラー": 7.4,
  "ドリームゴーズオン": 64.5,
  "パンサーズ": 7.9,
  "ナインオブレター": 54.3,
  "メイショウサトノヒ": 5.2,
  "キャットテイル": 15.3,
  "ブルージュ": 15.5,
  "ディーエストッキー": 28.2,
  "サイモンプレジール": 107.2,
  "チェルシー": 5.3,
  "ゼットスパンキー": 21.5,
  "ヴィヴァシャス": 18.4,
  "ミライハーモニー": 9.9,
  "パッションディーバ": 35.7,
  "ダディーズグーグー": 11.7,
  "オンサイト": 25.1,
  "リッキースタイル": 4.7,
  "グランデスフィーダ": 8.7,
  "ルクソンライト": 24.3,
  "ツクバヴァンガード": 4.5,
  "ソーマッチ": 223.3,
  "ヴェントディルーナ": 225.9,
  "アドミ": 10.1,
  "ピコレーヴ": 55.1,
  "ディサイドオンミー": 30.2,
  "アイムインディ": 2.5,
  "トレンドマーチ": 105.6,
  "ピコランド": 4.4,
  "ペイシャクロス": 150.3,
  "セキテイロックス": 7.9,
  "ユーベルジーク": 59.1,
  "プレヒティヒ": 152.6,
  "テンカラットレター": 363.5,
  "ホウオウチャールズ": 18.3,
  "ウインテラジーナ": 13.3,
  "クイーンズパーク": 106.3,
  "リリーサー": 12.2,
  "サトノスターライト": 7.7,
  "ルージュラベル": 9.1,
  "ノアシルヴィ": 74.9,
  "ジェムシリカ": 24.4,
  "ベアサナエチャン": 6.6,
  "ヘリオドール": 122.8,
  "フーディエラン": 34.4,
  "ダイヤテソーロ": 16.3,
  "ロジタイガー": 110.3,
  "ストームアイ": 126.2,
  "クレアノア": 4.1,
  "ソレム": 26.5,
  "ダノンアスコルティ": 5.1,
  "ペルシアーノ": 25.9,
  "ジュリ": 62.3,
  "マトリカリア": 69.1,
  "アテナガール": 26.2,
  "カキュウ": 79.5,
  "レッドフリーマン": 8.7,
  "クリアーゲイル": 12.0,
  "ブリサマリーナ": 6.1,
  "ルーリングクラス": 2.3,
  "サツキマーメイド": 91.4,
  "ブルージェネシス": 72.8,
  "オケアノステソーロ": 60.4,
  "ブライスフェアリー": 24.9,
  "ファインブライト": 22.9,
  "ジュナベーラ": 4.2,
  "レガリーノ": 24.9,
  "レピュニット": 15.7,
  "チームユートピア": 12.1,
  "ラインジーク": 14.2,
  "リアライズタキオン": 20.8,
  "クラディスティーナ": 46.1,
  "ヘリテージブルーム": 1.6,
  "タイセイエキサイト": 112.1,
  "マサノピンクレディ": 26.1,
  "ベルゼビュート": 8.1,
  "タイセイブルーム": 60.1,
  "マウンテンドーター": 174.5,
  "パータリプトラ": 27.6,
  "リアライズブラーヴ": 14.3,
  "スノースコール": 17.4,
  "ムーンストラック": 18.2,
  "ポッポノフェスタ": 29.2,
  "ラファミリア": 33.1,
  "ジェロニモス": 14.1,
  "ライヴスプーン": 79.2,
  "ヘルツアス": 95.0,
  "サンセットビュー": 8.5,
  "ポルトフェリス": 11.5,
  "マイネルアウルム": 12.2,
  "ウィンスタンリー": 20.6,
  "ウーバーストロング": 87.2,
  "イリュストル": 26.4,
  "キロノヴァ": 27.0,
  "ニヴルヘイム": 19.4,
  "ストレートブラック": 13.4,
  "サラコスティ": 3.0,
  "ガンバルマン": 6.0,
  "スカイハイ": 5.8,
  "サトミノキラリ": 15.8,
  "コートアリシアン": 3.9,
  "トーセンエスクード": 12.0,
  "エイムフォーエース": 34.2,
  "レッドエヴァンス": 6.0,
  "コスモサガルマータ": 24.0,
  "コスモアディラート": 66.8,
  "グーテンベルク": 9.7,
  "モーデン": 23.6,
  "ピコローズ": 9.0,
  "ポエットリー": 30.1,
  "ウインオーディン": 18.9,
  "ユハンヌス": 11.0,
  "ミツカネベネラ": 309.1,
  "レイクラシック": 82.6,
  "アランカール": 11.5,
  "ロングトールサリー": 152.4,
  "リアライズルミナス": 91.4,
  "ロンギングセリーヌ": 207.2,
  "スタニングレディ": 224.8,
  "スマートプリエール": 30.9,
  "トリニティ": 45.7,
  "スターアニス": 3.1,
  "アメティスタ": 110.6,
  "ドリームコア": 7.4,
  "エンネ": 6.9,
  "ソルパッサーレ": 192.1,
  "アンジュドジョワ": 25.6,
  "ジュウリョクピエロ": 7.4,
  "スウィートハピネス": 83.2,
  "ラフターラインズ": 3.6,
  "ハヤブササキチャン": 2.1,
  "アスクウルトラモア": 411.3,
  "タイムレスフレアー": 6.5,
  "ブランチアウト": 6.5,
  "ルージュソムニウム": 86.1,
  "エイシンリーガル": 193.0,
  "ゴッドレイ": 29.2,
  "ピンクパンサー": 157.8,
  "フィエスタ": 26.9,
  "アズライトアスール": 347.3,
  "キボウホー": 6.3,
  "ミキノヒストリー": 523.3,
  "モズガネシア": 265.0,
  "パラフローラ": 144.5,
  "リン": 10.7,
  "メイショウノヴァス": 9.5,
  "ユウトザイシン": 203.8,
  "ジュエルブリス": 64.1,
  "スノースケープ": 1.7,
  "シャリキモン": 17.7,
  "アメジストブリエ": 18.8,
  "カヴァティーナ": 26.2,
  "スフィダンテ": 21.8,
  "ダノンワンダー": 8.8,
  "マコトエウロペ": 15.3,
  "ナムラシンジロー": 51.5,
  "ヘブンクローバー": 91.4,
  "ティタノマキア": 3.7,
  "マテンロウギフト": 13.8,
  "ジャズ": 4.9,
  "キーウェーブ": 32.4,
  "ロゼル": 33.7,
  "ショウナンバルドル": 5.5,
  "ナイトスラッガー": 7.1,
  "ツーエムクロノス": 31.7,
  "ジョイエッロ": 3.1,
  "アラタマフェーヴル": 6.9,
  "メイショウヤシマ": 25.1,
  "クスクス": 15.0,
  "イミュータブル": 67.2,
  "メイショウヤーキス": 17.1,
  "ワンダラー": 7.6,
  "スノーサイレンス": 24.3,
  "ルクスデイジー": 10.3,
  "トーアジョウトウ": 12.0,
  "サザンエルフ": 43.8,
  "シャカシャカシー": 46.4,
  "ジャーヴィス": 32.9,
  "クアトロジャック": 27.8,
  "ハクサンアイリス": 8.1,
  "アンズアメ": 3.5,
  "エンヤラヴフェイス": 13.3,
  "ゲイルライダー": 4.2,
  "ショウナンザナドゥ": 24.8,
  "ガイアメンテ": 6.1,
  "スズカダブル": 14.0,
  "アンリーロード": 20.6,
  "アサヒ": 28.5,
  "ナムラエイハブ": 8.1,
  "オーロラエックス": 10.1,
  "メリオーレム": 11.7,
  "コパノサントス": 50.8,
  "チェルビアット": 6.0,
  "ショウナンマグマ": 30.1,
  "ジーティーアダマン": 3.2,
  "ゴンバデカーブース": 16.0
}